Pygalume-0.2.5.dist-info/WHEEL
Pygalume-0.2.5.dist-info/METADATA
Pygalume-0.2.5.dist-info/RECORD
Pygalume-0.2.5.dist-info/metadata.json
Pygalume-0.2.5.dist-info/top_level.txt
Pygalume-0.2.5.dist-info/DESCRIPTION.rst
pygalume/pygalume.py
pygalume/__init__.py
pygalume/settings.py
pygalume/myexceptions.py
pygalume/command_line.py
pygalume/tests/__init__.py
pygalume/tests/test_models.py
pygalume/tests/test_database.py
pygalume/tests/test_factory.py
pygalume/tests/test_utils.py
pygalume/tests/test_api.py
pygalume/models/__init__.py
pygalume/models/BaseModify.py
pygalume/models/lyrics.py
pygalume/controller/__init__.py
pygalume/controller/database.py
pygalume/controller/factory.py
pygalume/controller/api.py
pygalume/controller/utils.py
Pygalume-0.2.5.data/scripts/pygalume
