Metadata-Version: 2.0
Name: Pygalume
Version: 0.2.5
Summary: Pygalume is a simple Python CLI to get lyrics
Home-page: https://github.com/dunderlabs/pygalume
Author: Dunderlabs Team
Author-email: dunderlabs@gmail.com
License: MIT
Download-URL: https://pypi.python.org/pypi/Pygalume
Keywords: pygalume cli lyrics shell vagalume music song
Platform: windows linux
Classifier: Development Status :: 4 - Beta
Classifier: Intended Audience :: Developers
Classifier: Topic :: System :: Shells
Classifier: Programming Language :: Python :: 2.7
Classifier: Programming Language :: Python :: 3.3
Classifier: Programming Language :: Python :: 3.4
Classifier: Programming Language :: Python :: 3.5
Requires-Dist: requests (>=2.7.0)
Requires-Dist: peewee (>=2.8.0)
